stbz_lib/__init__.py
stbz_lib/_capture.py
stbz_lib/_close.py
stbz_lib/_kb.py
stbz_lib/_mic.py
stbz_lib/_mouse.py
stbz_lib/_shutdown.py
stbz_lib/_core/_hook.py
stbz_lib/_core/_win32.py
stbz_lib-0.2.1.dist-info/licenses/LICENSE
stbz_lib-0.2.1.dist-info/METADATA
stbz_lib-0.2.1.dist-info/WHEEL
stbz_lib-0.2.1.dist-info/top_level.txt
stbz_lib-0.2.1.dist-info/RECORD
