Metadata-Version: 2.4
Name: stbz_lib
Version: 0.2.1
Requires-Python: >=3.12
License-File: LICENSE
Requires-Dist: numpy==2.3.0
Dynamic: license-file
